NoLossAsyncGenerator/NoLossAsyncGenerator.py
NoLossAsyncGenerator/__init__.py
NoLossAsyncGenerator-2.4.dist-info/LICENSE
NoLossAsyncGenerator-2.4.dist-info/METADATA
NoLossAsyncGenerator-2.4.dist-info/WHEEL
NoLossAsyncGenerator-2.4.dist-info/top_level.txt
NoLossAsyncGenerator-2.4.dist-info/RECORD
